{
  "identity": {
    "id": "ed1bd490-1411-4dbf-944d-2ebc0dd955e9",
    "name": "system1"
  },
  "object": {
    "parent": {
      "id": "23b15add-f3a9-45ee-a4d5-ab4dfe8b87fb",
      "name": "/organizations/localDBTest2"
    },
    "tags": [],
    "documents": [],
    "type": "System",
    "properties": [],
    "history": {
      "created": "2020-12-07T22:21:36.927",
      "createdBy": "m.vorobiov@spd-ukraine.com",
      "updated": "2020-12-07T22:21:36.927",
      "updatedBy": "m.vorobiov@spd-ukraine.com",
      "completions": []
    }
  }
}